MANIFEST.in
README.rst
djob.py
setup.py
djob.egg-info/PKG-INFO
djob.egg-info/SOURCES.txt
djob.egg-info/dependency_links.txt
djob.egg-info/entry_points.txt
djob.egg-info/requires.txt
djob.egg-info/top_level.txt
djob.egg-info/zip-safe