Metadata-Version: 1.0
Name: djob
Version: 0.2.3
Summary: djob
Home-page: https://example.org
Author: me
Author-email: me@example.org
License: LGPL v3
Keywords: djob
Platform: UNKNOWN
